proxidize_wrapper/__init__.py
proxidize_wrapper/proxidize_wrapper.py
proxidize_wrapper-0.2.0.dist-info/LICENSE
proxidize_wrapper-0.2.0.dist-info/METADATA
proxidize_wrapper-0.2.0.dist-info/WHEEL
proxidize_wrapper-0.2.0.dist-info/top_level.txt
proxidize_wrapper-0.2.0.dist-info/RECORD
