Metadata-Version: 2.1
Name: proxidize-wrapper
Version: 0.2.0
Summary: Wrapper for proxidize android app.
Home-page: https://github.com/AG4lyf/proxidize_wrapper
Author: Suraj Bhari
Author-email: surajbhari159@gmail.com
License: MIT license
Keywords: proxidize_wrapper
Platform: UNKNOWN
Classifier: Development Status :: 2 - Pre-Alpha
Classifier: Intended Audience :: Developers
Classifier: License :: OSI Approved :: MIT License
Classifier: Natural Language :: English
Classifier: Programming Language :: Python :: 3
Classifier: Programming Language :: Python :: 3.6
Classifier: Programming Language :: Python :: 3.7
Classifier: Programming Language :: Python :: 3.8
Requires-Python: >=3.6
License-File: LICENSE
